{
    "master": {
        "btnAdd": "新規追加",
        "btnExcelImport": "Excelインポート",
        "btnDelete": "削除",
        "btnEdit": "編集",
        "btnCancel": "キャンセル",
        "btnSave": "保存",

        "costNum": "番号",
        "costCode": "経費",
        "costTypeJP": "分類（日本語）",
        "costNameJP": "経費（日本語）",
        "costTypeVN": "分類（ベトナム語）",
        "costNameVN": "経費（ベトナム語）",
        "costTimePeriods": "予算確認期間",
        "costYear": "年",

        "codeNum": "STT",
        "codeCode": "コード",
        "codeType": "コードタイプ",
        "codeName": "名前",
        "editDate": "編集日",
        "editor": "編集者",

        "customerNum": "番号",
        "customerCode": "顧客番号",
        "customerJPName": "顧客名 - 正式名称 / 日本語・英語",
        "customerVNName": "顧客名 - 正式名称 / ベトナム語",
        "customerShortName": "顧客名 - 簡易",
        "customerLocation": "分類",
        "customerAddress": "住所",
        "accountant": "会計担当者",
        "accountantName": "氏名",
        "accountantPhone": "電話番号",
        "accountantEmail": "メールアドレス",

        "retailerNum": "番号",
        "retailerCode": "税コード",
        "retailerJPName": "顧客名 - 正式名称 / 日本語・英語",
        "retailerVNName": "顧客名 - 正式名称 / ベトナム語",
        "retailerShortName": "顧客名 - 簡易",
        "retailerLocation": "分類",
        "retailerAddress": "住所",

        "applyYear": "適用年",
        "searchByCost": "コストコードで検索",
        "searchByCode": "コードタイプまたはコード名で検索",
        "searchByCustomerCode": "顧客コード、顧客名、または略称で検索",
        "searchByRetailerCode": "仕入先コード、仕入先名、または略称で検索",
        "dragAndDropFile": "ファイルをアップロードするか、ここにドラッグ＆ドロップしてください",
        "maxFileSize": "最大ファイルサイズは20MBです",
        "fileType": "Excelファイルのみ対応",
        "fileUploadSuccess": "ファイルのアップロードに成功しました。",
        "fileUploadError": "ファイルのアップロードに失敗しました。",
        "importSuccess": "ファイルのインポートが成功しました。",
        "importError": "ファイルのインポートに失敗しました。",
        "addSuccess": "新規追加が完了しました。",
        "addError": "新規追加に失敗しました。",
        "editSuccess": "編集が完了しました。",
        "editError": "編集に失敗しました。",
        "deleteSuccess": "削除が完了しました。",
        "deleteError": "削除に失敗しました。",
        "confirmDelete": "本当に削除してもよろしいですか？",
        "confirmDeleteAll": "全てを削除してもよろしいですか？",
        "confirmDeleteSelected": "選択した項目を削除してもよろしいですか？"
    }
}
